evogfuzz/__init__.py
evogfuzz/cli.py
evogfuzz/evogfuzz_class.py
evogfuzz/fitness_functions.py
evogfuzz/grammar_transformation.py
evogfuzz/helper.py
evogfuzz/input.py
evogfuzz/oracle.py
evogfuzz/tournament_selection.py
evogfuzz/type_defs.py
evogfuzz/types.py
evogfuzz/visualization.py
evogfuzz_formalizations/__init__.py
evogfuzz_formalizations/calculator.py
evogfuzz-0.6.0.dist-info/METADATA
evogfuzz-0.6.0.dist-info/WHEEL
evogfuzz-0.6.0.dist-info/entry_points.txt
evogfuzz-0.6.0.dist-info/top_level.txt
evogfuzz-0.6.0.dist-info/RECORD
