Metadata-Version: 2.1
Name: evogfuzz
Version: 0.6.0
Summary: Evolutionary Grammar-Based Fuzzer
Home-page: https://github.com/martineberlein/evogfuzz
Author: Martin Eberlein
Author-email: martin.eberlein@informatik.hu-berlin.de
License: MIT License
Project-URL: Bug Tracker, https://github.com/martineberlein/evogfuzz/issues
Classifier: Intended Audience :: Science/Research
Classifier: License :: OSI Approved :: MIT License
Classifier: Programming Language :: Python :: 3.10
Classifier: Operating System :: OS Independent
Classifier: Topic :: Scientific/Engineering
Classifier: Topic :: Software Development :: Testing
Requires-Dist: fuzzingbook (~=1.1)
Requires-Dist: jupyter
Requires-Dist: isla-solver
Provides-Extra: dev
Requires-Dist: pytest (>=7.2.0) ; extra == 'dev'
Requires-Dist: twine ; extra == 'dev'
